syntaxmod/__init__.py
syntaxmod/general.py
syntaxmod-0.1.0.dist-info/licenses/LICENSE
syntaxmod-0.1.0.dist-info/METADATA
syntaxmod-0.1.0.dist-info/WHEEL
syntaxmod-0.1.0.dist-info/top_level.txt
syntaxmod-0.1.0.dist-info/RECORD
